.gitignore
.pre-commit-config.yaml
.pylintrc
.readthedocs.yaml
CODE_OF_CONDUCT.md
LICENSE
README.rst
README.rst.license
pyproject.toml
requirements.txt
setup.py
sparkfun_qwiictwist.py
.github/PULL_REQUEST_TEMPLATE/adafruit_circuitpython_pr.md
.github/workflows/build.yml
.github/workflows/failure-help-text.yml
.github/workflows/release.yml
LICENSES/CC-BY-4.0.txt
LICENSES/MIT.txt
LICENSES/Unlicense.txt
docs/api.rst
docs/api.rst.license
docs/conf.py
docs/examples.rst
docs/examples.rst.license
docs/index.rst
docs/index.rst.license
docs/requirements.txt
docs/_static/favicon.ico
docs/_static/favicon.ico.license
examples/example10_i2c_scanner.py
examples/example1_basic_readings.py
examples/example2_set_color.py
examples/example3_crazy_color.py
examples/example4_connect_colors.py
examples/example5_timestamps.py
examples/example6_difference.py
examples/example7_set_count.py
examples/example8_interrupts.py
examples/example9_change_i2c_address.py
examples/qwiictwist_simpletest.py
sparkfun_circuitpython_qwiictwist.egg-info/PKG-INFO
sparkfun_circuitpython_qwiictwist.egg-info/SOURCES.txt
sparkfun_circuitpython_qwiictwist.egg-info/dependency_links.txt
sparkfun_circuitpython_qwiictwist.egg-info/requires.txt
sparkfun_circuitpython_qwiictwist.egg-info/top_level.txt